DOCUMENTATION.md
LICENSE
binypt/__init__.py
binypt/binypt.py
binypt/metadata/__init__.py
binypt/metadata/_metadata.py
binypt/metadata/_parser.py
binypt/metadata/_validator.py
binypt/metadata/metadata.json
binypt/progress_bar_wrapper.py
binypt/retriever.py
binypt_lib-2.3.7.dist-info/LICENSE
binypt_lib-2.3.7.dist-info/METADATA
binypt_lib-2.3.7.dist-info/WHEEL
binypt_lib-2.3.7.dist-info/RECORD
